datacatalog_custom_model_manager/__init__.py
datacatalog_custom_model_manager/custom_model_manager_cli.py
datacatalog_custom_model_manager-0.1.1.dist-info/LICENSE
datacatalog_custom_model_manager-0.1.1.dist-info/METADATA
datacatalog_custom_model_manager-0.1.1.dist-info/WHEEL
datacatalog_custom_model_manager-0.1.1.dist-info/entry_points.txt
datacatalog_custom_model_manager-0.1.1.dist-info/top_level.txt
datacatalog_custom_model_manager-0.1.1.dist-info/RECORD
