Metadata-Version: 2.1
Name: datacatalog-custom-model-manager
Version: 0.1.1
Summary: A package to load user-specified metadata models into Google Cloud Data Catalog
Home-page: https://github.com/ricardolsmendes/datacatalog-custom-model-manager
Author: Ricardo Mendes
Author-email: ricardolsmendes@gmail.com
License: MIT
Platform: Posix; MacOS X; Windows
Classifier: Development Status :: 3 - Alpha
Classifier: License :: OSI Approved :: MIT License
Classifier: Natural Language :: English
Classifier: Operating System :: OS Independent
Classifier: Programming Language :: Python
Classifier: Programming Language :: Python :: 3.6
Classifier: Programming Language :: Python :: 3.7
Classifier: Programming Language :: Python :: 3.8
Requires-Python: >=3.6
Requires-Dist: datacatalog-custom-entries-manager (~=0.1.2)
Requires-Dist: datacatalog-tag-manager (~=2.1.2)
Requires-Dist: datacatalog-tag-template-processor (~=0.2.0)
Requires-Dist: numpy (<=1.19.3,>=1.19.0)
Requires-Dist: pandas (~=1.1.4)
